{
    "bookList": [
      {
        "id": 1,
        "Author_Name": "Robin Sharma",
        "title": "5AM CLUB",
        "description": "Follow for better routine and a concise plot summary of the book.",
        "PageCount": 100,
        "price": 1110,
        "ISBN": 139780062312686
      },
  
      {
        "id": 2,
        "Author_Name":  "Aravind Adiga",
        "title": "The White Tiger",
        "description": "The Secret of Success.",
        "PageCount": 200,
        "price": 140.00,
        "ISBN": 1397807682312686
      },
  
      {
        "id": 3,
        "Author_Name": "Robert Kiyosaki",
        "title": "Rich Dad Poo Dad. ",
        "description": "Growing up with two dads",
        "PageCount": 800,
        "price": 514.00,
        "ISBN": 13978076823126786
      },
  
      {
        "id": 4,
        "Author_Name": "Ashley Hay",
        "title": "The Railwayman's Wife",
        "description": "Small Stories",
        "PageCount": 600,
        "price": 25.9,
        "ISBN": 5437807682312686
      },
  
      {
        "id": 5,
        "Author_Name": "Salman Rusddie",
        "title": "Midnight Slums",
        "description": "Slums Story",
        "PageCount": 650,
        "price": 110.9,
        "ISBN": 16547807682312686
      },
  
      {
        "id": 6,
        "Author_Name": "Russell H. Conwell",
        "title": "Acres Of Diamonds",
        "description": "Grey World",
        "PageCount": 120,
        "price": 49.9,
        "ISBN": 9317807682312686
      },
  
      {
        "id": 7,
        "Author_Name": "Keshari Nath",
        "title": "The Wings of Age",
        "description": "1977 War story",
        "PageCount": 900,
        "price": 22.5,
        "ISBN": 3997807682312686
      },
  
      {
        "id": 8,
        "Author_Name": "Michael Antony",
        "title": "Every Life Matters",
        "description": "",
        "PageCount":766,
        "price": 18.7,
        "ISBN": 7897807682312686
      },
      {
        "id": 9,
        "Author_Name": "Jo Nesbo",
        "title": "The Snowman",
        "description": "British crime thriller",
        "PageCount": 1000,
        "price": 134.9,
        "ISBN": 3897807682312686
      },
      {
        "id": 10,
        "Author_Name": "Suhail Abidi",
        "title": "What If Not I.I.T.?",
        "description": "Education",
        "PageCount": 1000,
        "price": 1440,
        "ISBN": 3897807682312686
      },
      {
        "id": 11,
        "Author_Name": "ANAND KUMAR",
        "title": "THE JOURNEY TIMES",
        "description": "Literature & Fiction",
        "PageCount": 1000,
        "price": 1340,
        "ISBN": 3897807682312686
      },
      {
        "id": 12,
        "Author_Name": "Andrew Deosty",
        "title": "The Rudest Book Ever",
        "description": "Literature & Fiction",
        "PageCount": 1000,
        "price": 130,
        "ISBN": 3897807682312686
      },
      {
        "id": 13,
        "Author_Name": "Viktor E Frankl",
        "title": "Mans Search Meaning",
        "description": "Fiction",
        "PageCount": 1300,
        "price": 134.9,
        "ISBN": 3897807682312686
      },
      {
        "id": 14,
        "Author_Name": "Amish Tripathi",
        "title": "Oath of Vayuputras",
        "description": "British crime thriller",
        "PageCount": 1000,
        "price": 134.9,
        "ISBN": 3897807682312686
      },
      {
        "id": 15,
        "Author_Name": "Charles Darwin",
        "title": "The Origin of Species",
        "description": "British crime thriller",
        "PageCount": 1000,
        "price": 134.9,
        "ISBN": 3897807682312686
      },
      {
        "id": 16,
        "Author_Name": "F. Scott Fitzgerald",
        "title": "The Great Gatsby",
        "description": "British crime thriller",
        "PageCount": 1000,
        "price": 134.9,
        "ISBN": 3897807682312686
      },
      {
        "id": 17,
        "Author_Name": "Charles Dickens",
        "title": "Hard Times ",
        "description": "British crime thriller",
        "PageCount": 1000,
        "price": 134.9,
        "ISBN": 3897807682312686
      },
      {
        "id": 18,
        "Author_Name": "Fredrik Backman",
        "title": "A Man Called Ove",
        "description": "British crime thriller",
        "PageCount": 1000,
        "price": 134.9,
        "ISBN": 3897807682312686
      },
      {
        "id": 19,
        "Author_Name": "Bakhtiar K. Dadab",
        "title": "A Life of J.R.D. Tata",
        "description": "British crime thriller",
        "PageCount": 1000,
        "price": 134.9,
        "ISBN": 3897807682312686
      },
      {
        "id": 20,
        "Author_Name": "Barack Obama",
        "title": "A Promised Land ",
        "description": "British crime thriller",
        "PageCount": 1000,
        "price": 450,
        "ISBN": 3897807682312686
      },
      {
        "id": 21,
        "Author_Name": "Jaishankar S",
        "title": "The India Way",
        "description": "British crime thriller",
        "PageCount": 1000,
        "price": 1100,
        "ISBN": 3897807682312686
      },
      {
        "id": 22,
        "Author_Name": "Kim Ghattas",
        "title": "Black Wave",
        "description": "British crime thriller",
        "PageCount": 1000,
        "price": 134.9,
        "ISBN": 3897807682312686
      },
      {
        "id": 23,
        "Author_Name": "Douglas Murray",
        "title": "Madness of Crowds",
        "description": "British crime thriller",
        "PageCount": 1000,
        "price": 134.9,
        "ISBN": 3897807682312686
      },
      {
        "id": 24,
        "Author_Name": "Michael J. Sandel ",
        "title": "The Tyranny of Merit",
        "description": "British crime thriller",
        "PageCount": 1000,
        "price": 134.9,
        "ISBN": 3897807682312686
      },
      {
        "id": 25,
        "Author_Name": "Amrit Raj",
        "title": "Indian Icon",
        "description": "British crime thriller",
        "PageCount": 1000,
        "price": 1500,
        "ISBN": 3897807682312686
      }

    ]
  }